[{"bbox_2d":[336,709,358,799],"label":"window"},{"bbox_2d":[446,710,468,800],"label":"window"},{"bbox_2d":[482,710,504,800],"label":"window"},{"bbox_2d":[446,549,468,638],"label":"window"},{"bbox_2d":[482,549,504,638],"label":"window"},{"bbox_2d":[558,721,581,810],"label":"window"},{"bbox_2d":[598,721,620,810],"label":"window"},{"bbox_2d":[638,721,660,810],"label":"window"},{"bbox_2d":[558,570,581,660],"label":"window"},{"bbox_2d":[598,570,620,660],"label":"window"},{"bbox_2d":[638,570,660,660],"label":"window"},{"bbox_2d":[558,420,581,509],"label":"window"},{"bbox_2d":[598,420,620,509],"label":"window"},{"bbox_2d":[638,420,660,509],"label":"window"}]