[
    {
        "bbox_2d": [
            478,
            613,
            491,
            661
        ],
        "label": "window"
    },
    {
        "bbox_2d": [
            539,
            613,
            553,
            661
        ],
        "label": "window"
    },
    {
        "bbox_2d": [
            447,
            480,
            461,
            527
        ],
        "label": "window"
    },
    {
        "bbox_2d": [
            478,
            480,
            491,
            527
        ],
        "label": "window"
    },
    {
        "bbox_2d": [
            509,
            480,
            522,
            527
        ],
        "label": "window"
    },
    {
        "bbox_2d": [
            539,
            480,
            553,
            527
        ],
        "label": "window"
    }
]